pdf_generator/__main__.py
pdf_generator/convert.py
oneoneoneexample-0.8.dist-info/METADATA
oneoneoneexample-0.8.dist-info/WHEEL
oneoneoneexample-0.8.dist-info/top_level.txt
oneoneoneexample-0.8.dist-info/RECORD
