Metadata-Version: 2.1
Name: oneoneoneexample
Version: 0.8
Requires-Dist: pandas
Requires-Dist: jinja2
Requires-Dist: PyPDF2
Requires-Dist: pdfkit
